{
  "Header": {
    "language": "en",
    "IdLevel0": 0,
    "IdLevel1": 3,
    "IdLevel2": 1,
    "IdLevel3": 255
  },
  "LinkedVariable": "g_stFaultsVehicle_000_003_001_255_Battery_01_48V60TRX",
  "Version": 2,
  "FaultDetailList": [
    {
      "Description": "Battery charge: High temperature",
      "IsExpandable": false
    },
    {
      "Description": "Battery charge: Low temperature",
      "IsExpandable": false
    },
    {
      "Description": "Battery charge: Overtemperature",
      "IsExpandable": false
    },
    {
      "Description": "Battery charge: Overvoltage",
      "IsExpandable": false
    },
    {
      "Description": "Battery charge: Short-circuit",
      "IsExpandable": false
    },
    {
      "Description": "Battery charge: Other charging fault",
      "IsExpandable": false
    },
    {
      "Description": "Battery charge: MOSFET temperature",
      "IsExpandable": false
    },
    {
      "Description": "Battery charge: Severe under-voltage",
      "IsExpandable": false
    },
    {
      "Description": "Battery charge: Communication with AFE failed",
      "IsExpandable": false
    },
    {
      "Description": "Battery charge: Secondary protection against equipment overvoltage",
      "IsExpandable": false
    },
    {
      "Description": "Battery charge: Reserved",
      "IsExpandable": false
    },
    {
      "Description": "Battery charge: Pre-charge failure",
      "IsExpandable": false
    },
    {
      "Description": "Battery charge: Parallelism error of the pack",
      "IsExpandable": false
    },
    {
      "Description": "Battery charge: Overcharge Current Protection (OPC)",
      "IsExpandable": false
    },
    {
      "Description": "Battery charge: Pre-discharge failure",
      "IsExpandable": false
    },
    {
      "Description": "Battery charge: Internal communication failure",
      "IsExpandable": false
    },
    {
      "Description": "Battery discharge: High temperature",
      "IsExpandable": false
    },
    {
      "Description": "Battery discharge: Low temperature",
      "IsExpandable": false
    },
    {
      "Description": "Battery discharge: Overtemperature",
      "IsExpandable": false
    },
    {
      "Description": "Battery discharge: Under-voltage",
      "IsExpandable": false
    },
    {
      "Description": "Battery discharge: Short-circuit",
      "IsExpandable": false
    },
    {
      "Description": "Battery discharge: Other discharge fault",
      "IsExpandable": false
    },
    {
      "Description": "Battery discharge: MOSFET temperature",
      "IsExpandable": false
    },
    {
      "Description": "Battery discharge: Severe under-voltage",
      "IsExpandable": false
    },
    {
      "Description": "Battery discharge: Communication with AFE failed",
      "IsExpandable": false
    },
    {
      "Description": "Battery discharge: Secondary protection against equipment overvoltage",
      "IsExpandable": false
    },
    {
      "Description": "Battery discharge: Reserved",
      "IsExpandable": false
    },
    {
      "Description": "Battery discharge: Reserved",
      "IsExpandable": false
    },
    {
      "Description": "Battery discharge: Parallelism error of the pack",
      "IsExpandable": false
    },
    {
      "Description": "Battery discharge: Reserved",
      "IsExpandable": false
    },
    {
      "Description": "Battery discharge: Pre-discharge failure",
      "IsExpandable": false
    },
    {
      "Description": "Battery discharge: Internal communication failure",
      "IsExpandable": false
    }
  ]
}